[
  {
    "username": "@noha",
    "password": "password",
    "friends": [
      "@omar"
    ],
    "friendRequestsSent": [],
    "friendRequestsReceived": [],
    "challengesSent": [
      {
        "challengeId": "challenge-mbo4sh867rhunkki9",
        "opponentUsername": "@omar",
        "status": "active",
        "createdAt": "2025-06-08T20:44:11.190Z",
        "updatedAt": "2025-06-08T20:45:57.764Z",
        "activeGameId": "game-mbo4urgkql3e6cjzc"
      },
      {
        "challengeId": "challenge-mbo5kadt1lqmp6zk6",
        "opponentUsername": "@omar",
        "status": "active",
        "createdAt": "2025-06-08T21:05:48.689Z",
        "updatedAt": "2025-06-08T21:06:34.953Z",
        "activeGameId": "game-mbo5la2yspuk1oz6z"
      }
    ],
    "challengesReceived": []
  },
  {
    "username": "@omar",
    "password": "password",
    "friends": [
      "@noha"
    ],
    "friendRequestsSent": [],
    "friendRequestsReceived": [],
    "challengesSent": [],
    "challengesReceived": [
      {
        "challengeId": "challenge-mbo4sh867rhunkki9",
        "challengerUsername": "@noha",
        "status": "active",
        "createdAt": "2025-06-08T20:44:11.190Z",
        "updatedAt": "2025-06-08T20:45:57.764Z",
        "activeGameId": "game-mbo4urgkql3e6cjzc"
      },
      {
        "challengeId": "challenge-mbo5kadt1lqmp6zk6",
        "challengerUsername": "@noha",
        "status": "active",
        "createdAt": "2025-06-08T21:05:48.689Z",
        "updatedAt": "2025-06-08T21:06:34.953Z",
        "activeGameId": "game-mbo5la2yspuk1oz6z"
      }
    ]
  }
]